odoo8_addon_mass-8.0.0.1.0-py2.7-nspkg.pth
odoo_addons/mass/mass_demo.xml
odoo_addons/mass/__openerp__.py
odoo_addons/mass/report.xml
odoo_addons/mass/__init__.py
odoo_addons/mass/product_view.xml
odoo_addons/mass/mass_view.xml
odoo_addons/mass/company.py
odoo_addons/mass/mass_data.xml
odoo_addons/mass/mass.py
odoo_addons/mass/README.rst
odoo_addons/mass/company_view.xml
odoo_addons/mass/partner_view.xml
odoo_addons/mass/security/mass_security.xml
odoo_addons/mass/security/ir.model.access.csv
odoo_addons/mass/i18n/mass.pot
odoo_addons/mass/i18n/fr.po
odoo_addons/mass/wizard/swap_celebrant.py
odoo_addons/mass/wizard/validate_mass_journal_view.xml
odoo_addons/mass/wizard/validate_mass_journal.py
odoo_addons/mass/wizard/select_mass_requests_to_transfer_view.xml
odoo_addons/mass/wizard/select_mass_requests_to_transfer.py
odoo_addons/mass/wizard/generate_mass_journal_view.xml
odoo_addons/mass/wizard/swap_celebrant_view.xml
odoo_addons/mass/wizard/__init__.py
odoo_addons/mass/wizard/generate_mass_journal.py
odoo_addons/mass/test/generate_mass_journal.yml
odoo_addons/mass/views/report_massrequesttransfer.xml
odoo_addons/mass/views/report_massline.xml
odoo_addons/mass/static/description/icon.png
odoo8_addon_mass-8.0.0.1.0.dist-info/top_level.txt
odoo8_addon_mass-8.0.0.1.0.dist-info/WHEEL
odoo8_addon_mass-8.0.0.1.0.dist-info/RECORD
odoo8_addon_mass-8.0.0.1.0.dist-info/metadata.json
odoo8_addon_mass-8.0.0.1.0.dist-info/DESCRIPTION.rst
odoo8_addon_mass-8.0.0.1.0.dist-info/METADATA
odoo8_addon_mass-8.0.0.1.0.dist-info/namespace_packages.txt
